moat/lib/proxy/__init__.py
moat/lib/proxy/_impl.py
moat/lib/proxy/_proxy.py
moat_lib_proxy-0.1.0.dist-info/licenses/LICENSE.txt
moat_lib_proxy-0.1.0.dist-info/METADATA
moat_lib_proxy-0.1.0.dist-info/WHEEL
moat_lib_proxy-0.1.0.dist-info/top_level.txt
moat_lib_proxy-0.1.0.dist-info/RECORD
